pymds/__init__.py
pymds/mds.py
pymds-0.1.6.dist-info/METADATA
pymds-0.1.6.dist-info/RECORD
pymds-0.1.6.dist-info/WHEEL
pymds-0.1.6.dist-info/top_level.txt
pymds-0.1.6.dist-info/zip-safe
